wrapper_vjwhats/__init__.py
wrapper_vjwhats/elements.py
wrapper_vjwhats/whatsapp.py
wrapper_vjwhats-0.0.6.dist-info/licenses/LICENSE
wrapper_vjwhats-0.0.6.dist-info/METADATA
wrapper_vjwhats-0.0.6.dist-info/WHEEL
wrapper_vjwhats-0.0.6.dist-info/top_level.txt
wrapper_vjwhats-0.0.6.dist-info/RECORD
