Metadata-Version: 2.4
Name: wrapper-vjwhats
Version: 0.0.6
Summary: Wrapper for vjwhats library to send messages and sent messages
Home-page: https://github.com/Renan-RodriguesDEV/wrapper-vjwhats
Author: Renan Rodrigues
Author-email: renanrodrigues7110@gmail.com
License: MIT
Classifier: Programming Language :: Python :: 3
Classifier: License :: OSI Approved :: MIT License
Classifier: Operating System :: OS Independent
Requires-Python: >=3.13.0
License-File: LICENSE
Requires-Dist: selenium>=4.39.0
Requires-Dist: pyperclip>=1.11.0
Dynamic: author
Dynamic: author-email
Dynamic: classifier
Dynamic: description
Dynamic: description-content-type
Dynamic: home-page
Dynamic: license
Dynamic: license-file
Dynamic: requires-dist
Dynamic: requires-python
Dynamic: summary
